Metadata-Version: 2.1
Name: turtletext
Version: 0.0.7
Summary: A turtle writes text.
Home-page: UNKNOWN
License: UNKNOWN
Platform: UNKNOWN
Classifier: Programming Language :: Python :: 3.7
Classifier: License :: OSI Approved :: MIT License
Classifier: Operating System :: OS Independent
